learning_orchestra_client/__init__.py
learning_orchestra_client/_util/__init__.py
learning_orchestra_client/_util/_entity_reader.py
learning_orchestra_client/_util/_response_treat.py
learning_orchestra_client/builder/__init__.py
learning_orchestra_client/builder/builder.py
learning_orchestra_client/dataset/__init__.py
learning_orchestra_client/dataset/_dataset.py
learning_orchestra_client/dataset/csv.py
learning_orchestra_client/dataset/generic.py
learning_orchestra_client/evaluate/__init__.py
learning_orchestra_client/evaluate/_evaluate.py
learning_orchestra_client/evaluate/scikitlearn.py
learning_orchestra_client/evaluate/tensorflow.py
learning_orchestra_client/explore/__init__.py
learning_orchestra_client/explore/_explore.py
learning_orchestra_client/explore/histogram.py
learning_orchestra_client/explore/scikitlearn.py
learning_orchestra_client/explore/tensorflow.py
learning_orchestra_client/function/__init__.py
learning_orchestra_client/function/python.py
learning_orchestra_client/model/__init__.py
learning_orchestra_client/model/_model.py
learning_orchestra_client/model/scikitlearn.py
learning_orchestra_client/model/tensorflow.py
learning_orchestra_client/observe/__init__.py
learning_orchestra_client/observe/observe.py
learning_orchestra_client/predict/__init__.py
learning_orchestra_client/predict/_predict.py
learning_orchestra_client/predict/scikitlearn.py
learning_orchestra_client/predict/tensorflow.py
learning_orchestra_client/train/__init__.py
learning_orchestra_client/train/_train.py
learning_orchestra_client/train/scikitlearn.py
learning_orchestra_client/train/tensorflow.py
learning_orchestra_client/transform/__init__.py
learning_orchestra_client/transform/_transform.py
learning_orchestra_client/transform/data_type.py
learning_orchestra_client/transform/projection.py
learning_orchestra_client/transform/scikitlearn.py
learning_orchestra_client/transform/tensorflow.py
learning_orchestra_client-2.2.3.dist-info/LICENSE
learning_orchestra_client-2.2.3.dist-info/METADATA
learning_orchestra_client-2.2.3.dist-info/WHEEL
learning_orchestra_client-2.2.3.dist-info/top_level.txt
learning_orchestra_client-2.2.3.dist-info/RECORD
