Metadata-Version: 2.1
Name: learning-orchestra-client
Version: 2.2.3
Summary: learningOrchestra python client
Home-page: https://github.com/learningOrchestra/pythonClient
Author: Gabriel Ribeiro
Author-email: gabbriel.rribeiro@gmail.com
License: UNKNOWN
Platform: UNKNOWN
Classifier: Programming Language :: Python :: 3
Classifier: License :: OSI Approved :: GNU General Public License v3 (GPLv3)
Classifier: Operating System :: OS Independent
Requires-Python: >=3.8
